__init__.py
poetry.lock
pyproject.toml
setup.py
config/__init__.py
config/config.py
config/logging_config.py
data/DisasterResponse.db
data/disaster_response_messages.csv
disaster_message_classification_model.egg-info/PKG-INFO
disaster_message_classification_model.egg-info/SOURCES.txt
disaster_message_classification_model.egg-info/dependency_links.txt
disaster_message_classification_model.egg-info/requires.txt
disaster_message_classification_model.egg-info/top_level.txt
features/message_tokenizer.py
model/predict.py
model/train_model.py
trained_model/adaboost_model_v1.0.3.pkl
trained_model/performance_report/adaboost_model_v1.0.3_performance.csv
utils/__init__.py
utils/data_utils.py
utils/model_utils.py
utils/visuals_utils.py
visualizations/generate_visuals.py