Metadata-Version: 2.1
Name: disaster-message-classification-model
Version: 1.0.3
Summary: End to end lightGBM classification model to predict disaster message genres
Home-page: UNKNOWN
Author: Bowen
License: UNKNOWN
Platform: UNKNOWN
Requires-Python: ==3.*,>=3.7.0
Provides-Extra: dev
